hatchling/__about__.py
hatchling/__init__.py
hatchling/__main__.py
hatchling/build.py
hatchling/ouroboros.py
hatchling/py.typed
hatchling/bridge/__init__.py
hatchling/bridge/app.py
hatchling/builders/__init__.py
hatchling/builders/app.py
hatchling/builders/binary.py
hatchling/builders/config.py
hatchling/builders/constants.py
hatchling/builders/custom.py
hatchling/builders/macos.py
hatchling/builders/sdist.py
hatchling/builders/utils.py
hatchling/builders/wheel.py
hatchling/builders/hooks/__init__.py
hatchling/builders/hooks/custom.py
hatchling/builders/hooks/version.py
hatchling/builders/hooks/plugin/__init__.py
hatchling/builders/hooks/plugin/hooks.py
hatchling/builders/hooks/plugin/interface.py
hatchling/builders/plugin/__init__.py
hatchling/builders/plugin/hooks.py
hatchling/builders/plugin/interface.py
hatchling/cli/__init__.py
hatchling/cli/build/__init__.py
hatchling/cli/dep/__init__.py
hatchling/cli/dep/core.py
hatchling/cli/metadata/__init__.py
hatchling/cli/version/__init__.py
hatchling/dep/__init__.py
hatchling/dep/core.py
hatchling/metadata/__init__.py
hatchling/metadata/core.py
hatchling/metadata/custom.py
hatchling/metadata/spec.py
hatchling/metadata/utils.py
hatchling/metadata/plugin/__init__.py
hatchling/metadata/plugin/hooks.py
hatchling/metadata/plugin/interface.py
hatchling/plugin/__init__.py
hatchling/plugin/exceptions.py
hatchling/plugin/manager.py
hatchling/plugin/specs.py
hatchling/plugin/utils.py
hatchling/utils/__init__.py
hatchling/utils/constants.py
hatchling/utils/context.py
hatchling/utils/fs.py
hatchling/version/__init__.py
hatchling/version/core.py
hatchling/version/scheme/__init__.py
hatchling/version/scheme/standard.py
hatchling/version/scheme/plugin/__init__.py
hatchling/version/scheme/plugin/hooks.py
hatchling/version/scheme/plugin/interface.py
hatchling/version/source/__init__.py
hatchling/version/source/code.py
hatchling/version/source/env.py
hatchling/version/source/regex.py
hatchling/version/source/plugin/__init__.py
hatchling-1.26.2.dist-info/METADATA
hatchling-1.26.2.dist-info/WHEEL
hatchling-1.26.2.dist-info/entry_points.txt
hatchling-1.26.2.dist-info/licenses/LICENSE.txt
hatchling-1.26.2.dist-info/RECORD
